trubar/__init__.py
trubar/__main__.py
trubar/actions.py
trubar-0.1.2.dist-info/LICENSE
trubar-0.1.2.dist-info/METADATA
trubar-0.1.2.dist-info/WHEEL
trubar-0.1.2.dist-info/entry_points.txt
trubar-0.1.2.dist-info/top_level.txt
trubar-0.1.2.dist-info/RECORD
